modification_timekeeper/__init__.py
modification_timekeeper/cli.py
modification_timekeeper-0.1.2.dist-info/licenses/LICENSE
modification_timekeeper-0.1.2.dist-info/METADATA
modification_timekeeper-0.1.2.dist-info/WHEEL
modification_timekeeper-0.1.2.dist-info/entry_points.txt
modification_timekeeper-0.1.2.dist-info/top_level.txt
modification_timekeeper-0.1.2.dist-info/RECORD
