Metadata-Version: 2.4
Name: modification-timekeeper
Version: 0.1.2
Summary: Tool for keeping the modified time in front matter up to date.
Author-email: Stefanie Molin <modification-timekeeper@stefaniemolin.com>
License-Expression: MIT
Project-URL: Documentation, https://github.com/stefmolin/modification-timekeeper
Project-URL: Homepage, https://github.com/stefmolin/modification-timekeeper
Project-URL: Source, https://github.com/stefmolin/modification-timekeeper
Keywords: front matter,markdown,metadata,modification time,pre-commit
Classifier: Development Status :: 4 - Beta
Classifier: Programming Language :: Python
Classifier: Programming Language :: Python :: 3 :: Only
Classifier: Programming Language :: Python :: 3.9
Classifier: Programming Language :: Python :: 3.10
Classifier: Programming Language :: Python :: 3.11
Classifier: Programming Language :: Python :: 3.12
Classifier: Programming Language :: Python :: 3.13
Requires-Python: >=3.9
License-File: LICENSE
Requires-Dist: pyyaml
Provides-Extra: dev
Requires-Dist: pre-commit; extra == "dev"
Requires-Dist: pytest; extra == "dev"
Requires-Dist: pytest-cov; extra == "dev"
Requires-Dist: pytest-randomly; extra == "dev"
Dynamic: license-file
